examples/e01_number_types.py
examples/e02_custom_types.py
examples/e03_collection_types.py
examples/e04_mapping_types.py
examples/e05_pandas_numpy.py
examples/e06_file_wrapper.py
examples/e07_data_types_one.py
examples/e08_data_types_all.py
examples/e09_file_collection.py
examples/e10_file_data_types.py
examples/e11_nested_base_types.py
examples/e12_nested_complex_types.py
pyon/__init__.py
pyon/api.py
pyon/encoder.py
pyon/supported_types.py
pyon/utils.py
pyon/encoders/__init__.py
pyon/encoders/base_encoder.py
pyon/encoders/base_types.py
pyon/encoders/collection_types.py
pyon/encoders/datetime_types.py
pyon/encoders/mapping_types.py
pyon/encoders/numeric_types.py
pyon/encoders/specialized_types.py
pyon/file/__init__.py
pyon/file/api.py
pyon_core-0.2.6a1.dist-info/licenses/LICENSE
tests/test_api.py
tests/test_encoder.py
tests/test_file.py
tests/test_supported_types.py
tests/test_utils.py
tests/encoders/test_base_types.py
tests/encoders/test_collection_types.py
tests/encoders/test_datetime_types.py
tests/encoders/test_mapping_types.py
tests/encoders/test_numeric_types.py
tests/encoders/test_specialized_types.py
tmp/tmp_01.py
tmp/tmp_02.py
pyon_core-0.2.6a1.dist-info/METADATA
pyon_core-0.2.6a1.dist-info/WHEEL
pyon_core-0.2.6a1.dist-info/top_level.txt
pyon_core-0.2.6a1.dist-info/RECORD
