Metadata-Version: 2.4
Name: pyon-core
Version: 0.2.6a1
Summary: Python Object Notation: Extended JSON for complex Python types
Author-email: Eduardo Rodrigues <ietsira@eonflux.ai>
License-Expression: MIT
Project-URL: Homepage, https://github.com/eonflux-ai/pyon
Project-URL: Documentation, https://github.com/eonflux-ai/pyon#readme
Project-URL: Source, https://github.com/eonflux-ai/pyon
Project-URL: Tracker, https://github.com/eonflux-ai/pyon/issues
Keywords: serialization,deserialization,JSON,Python,AI,ML
Classifier: Development Status :: 3 - Alpha
Classifier: Intended Audience :: Developers
Classifier: Programming Language :: Python :: 3
Classifier: Programming Language :: Python :: 3.10
Classifier: Programming Language :: Python :: 3.11
Classifier: Programming Language :: Python :: 3.12
Classifier: Programming Language :: Python :: 3.13
Requires-Python: >=3.10
License-File: LICENSE
Requires-Dist: bitarray<4.0,>=3.0.0
Requires-Dist: numpy<3.0,>=2.2.0
Requires-Dist: pandas<3.0,>=2.2.0
Requires-Dist: python-magic-bin<0.5,>=0.4.14
Provides-Extra: dev
Requires-Dist: pytest; extra == "dev"
Requires-Dist: pytest-cov; extra == "dev"
Requires-Dist: black; extra == "dev"
Requires-Dist: pylint; extra == "dev"
Dynamic: license-file
